pysces/PyscesLink.py
pysces/PyscesWeb.py
pysces/PyscesPlot.py
pysces/version.py
pysces/PyscesContribUser.py
pysces/PyscesMiniModel.py
pysces/RateChar.py
pysces/PyscesSED.py
pysces/__init__.py
pysces/PyscesTest.py
pysces/PyscesJWSParse.py
pysces/PyscesStoich.py
pysces/PyscesRandom.py
pysces/PyscesParScan.py
pysces/PyscesContrib.py
pysces/PyscesSBML.py
pysces/PyscesPlot2.py
pysces/PyscesParse.py
pysces/PyscesScan.py
pysces/PyscesModelMap.py
pysces/version.txt
pysces/PyscesConfig.py
pysces/_multicorescan.py
pysces/PyscesModel.py
pysces/PyscesInterfaces.py
pysces/pyscfg.ini
pysces/PyscesUtils.py
pysces/nleq2/__init__.py
pysces/nleq2/nleq2_readme.txt
pysces/nleq2/readme.txt
pysces/nleq2/nleq2.cpython-310-darwin.so
pysces/tests/__init__.py
pysces/pscmodels/pysces_test_BIOMD126.xml
pysces/pscmodels/noisy_lin4.psc
pysces/pscmodels/pysces_test_branch1.psc
pysces/pscmodels/pysces_test_pitcon.psc
pysces/pscmodels/pysces_test_BIOMD860.xml
pysces/pscmodels/lin5_hill.psc
pysces/pscmodels/Burstmodel.psc
pysces/pscmodels/pysces_test_BIOMD012.xml
pysces/pscmodels/isola2a.psc
pysces/pscmodels/pysces_test_linear1.psc
pysces/pscmodels/pysces_test_moiety1.psc
pysces/docs/userguide.pdf
pysces/core2/yacc.py
pysces/core2/lex.py
pysces/core2/version.py
pysces/core2/InfixParser.py
pysces/core2/__init__.py
pysces/core2/PyscesCore2Interfaces.py
pysces/core2/PyscesCore2.py
pysces/core2/PyscesCore2Modules.py
pysces/contrib/__init__.py
pysces/contrib/demo/__init__.py
pysces/contrib/demo/demotest.py
pysces/.dylibs/libgfortran.5.dylib
pysces/.dylibs/libquadmath.0.dylib
pysces/.dylibs/libgcc_s.1.1.dylib
pysces/sandbox/__init__.py
pysces/sandbox/Intersect.py
pysces/examples/testRunScatter.py
pysces/examples/testinvalidstate.py
pysces/examples/benchmark.ipy
pysces/examples/testratechar.py
pysces/examples/parallelscan.ipy
pysces/examples/pysces_stochpy.py
pysces/examples/testparscanner.py
pysces/lib/yacc.py
pysces/lib/lex.py
pysces-1.2.3.dist-info/RECORD
pysces-1.2.3.dist-info/WHEEL
pysces-1.2.3.dist-info/METADATA
