Metadata-Version: 2.1
Name: pysces
Version: 1.2.3
Summary: The Python Simulator for Cellular Systems - simulation and analysis tools for modelling biological systems
Keywords: computational systems biology,modelling,simulation,systems biology
Author-Email: Brett Olivier <pysces@googlegroups.com>, Johann Rohwer <pysces@googlegroups.com>
Maintainer-Email: Brett Olivier <pysces@googlegroups.com>, Johann Rohwer <pysces@googlegroups.com>
License: BSD 3-Clause
Classifier: Development Status :: 5 - Production/Stable
Classifier: Development Status :: 6 - Mature
Classifier: Environment :: Console
Classifier: Intended Audience :: End Users/Desktop
Classifier: Intended Audience :: Science/Research
Classifier: License :: OSI Approved :: BSD License
Classifier: Natural Language :: English
Classifier: Operating System :: OS Independent
Classifier: Programming Language :: Fortran
Classifier: Programming Language :: Python
Classifier: Topic :: Scientific/Engineering :: Bio-Informatics
Classifier: Topic :: Scientific/Engineering :: Chemistry
Project-URL: homepage, https://pysces.github.io
Project-URL: documentation, https://pyscesdocs.readthedocs.io
Project-URL: source, https://github.com/PySCeS/pysces
Project-URL: download, https://github.com/PySCeS/pysces/releases
Project-URL: tracker, https://github.com/PySCeS/pysces/issues
Requires-Python: >=3.9
Requires-Dist: numpy>=1.23.5
Requires-Dist: matplotlib
Requires-Dist: scipy
Requires-Dist: numdifftools
Provides-Extra: parscan
Requires-Dist: ipyparallel; extra == "parscan"
Requires-Dist: multiprocessing_on_dill; extra == "parscan"
Provides-Extra: cvode
Requires-Dist: assimulo; extra == "cvode"
Provides-Extra: sbml
Requires-Dist: python_libsbml; extra == "sbml"
Provides-Extra: all
Requires-Dist: ipyparallel; extra == "all"
Requires-Dist: multiprocessing_on_dill; extra == "all"
Requires-Dist: assimulo; extra == "all"
Requires-Dist: python_libsbml; extra == "all"
